setup.py
mathomatic/__init__.py
mathomatic/mathomatic.py
mathomaticprimes.egg-info/PKG-INFO
mathomaticprimes.egg-info/SOURCES.txt
mathomaticprimes.egg-info/dependency_links.txt
mathomaticprimes.egg-info/top_level.txt