Metadata-Version: 1.0
Name: mathomaticprimes
Version: 0.0.1
Summary: Python library and web service interface (as service egg) for Mathomatic's prime number generator.
Home-page: http://gitorious.org/python-service-eggs
Author: Josef Spillner
Author-email: josef.spillner@tu-dresden.de
License: AGPLv3
Keywords: primes web service egg
Platform: UNKNOWN
Classifier: Development Status :: 2 - Pre-Alpha
Classifier: Environment :: No Input/Output (Daemon)
Classifier: Programming Language :: Python :: 2
Classifier: Topic :: Internet :: WWW/HTTP
Classifier: License :: OSI Approved :: GNU Affero General Public License v3
